txzmq/__init__.py
txzmq/compat.py
txzmq/connection.py
txzmq/factory.py
txzmq/pubsub.py
txzmq/pushpull.py
txzmq/req_rep.py
txzmq/router_dealer.py
txzmq/test/__init__.py
txzmq/test/test_connection.py
txzmq/test/test_factory.py
txzmq/test/test_pubsub.py
txzmq/test/test_reactor_shutdown.py
txzmq/test/test_reqrep.py
txzmq/test/test_router_dealer.py
txZMQ-1.0.0.dist-info/AUTHORS.txt
txZMQ-1.0.0.dist-info/LICENSE.txt
txZMQ-1.0.0.dist-info/METADATA
txZMQ-1.0.0.dist-info/WHEEL
txZMQ-1.0.0.dist-info/top_level.txt
txZMQ-1.0.0.dist-info/RECORD
