Metadata-Version: 2.1
Name: txZMQ
Version: 1.0.0
Summary: Twisted bindings for ZeroMQ
Home-page: https://github.com/smira/txZMQ
Author: Andrey Smirnov
Author-email: me@smira.ru
License: MPLv2
Platform: UNKNOWN
Classifier: Development Status :: 5 - Production/Stable
Classifier: Intended Audience :: Developers
Classifier: License :: OSI Approved :: Mozilla Public License 2.0 (MPL 2.0)
Classifier: Programming Language :: Python
Classifier: Programming Language :: Python :: 2
Classifier: Programming Language :: Python :: 3
Classifier: Topic :: Software Development :: Libraries
Requires-Dist: Twisted (>=10.0)
Requires-Dist: pyzmq (>=13)
